Test/IMEM_Test/imem.v
`timescale 1ns / 1ps

module imem(
input [31:0] a,
input IM_R,
output [31:0] rd
    );
   
    reg [31:0] RAM[2047:0];
    initial
    begin
      $readmemh("/Users/wayne/imem_test/imem.txt",RAM);
    end
    
   assign rd=(IM_R)?RAM[a[31:2]]:32'bx;
endmodule

Test/IMEM_Test/imem_tb.v
`timescale 1ns/1ps

module imem_tb (
    );
    reg IM_R;
    reg [31:0] a;
    wire [31:0] rd;
    integer i;
    initial begin
        $dumpfile("imem.vcd");
        $dumpvars(0, imem_tb);
    end
    initial begin
        a = 32'b0;
        IM_R = 1;
        for (i=0; i<60; i=i+1) begin
            #10 ;
            a = a + 32'd4;
        end
    end
    imem imem1(a, IM_R, rd);

endmodule

Test/IMEM_Test/imem.vcd
$date
	Wed Mar 23 22:48:52 2022
$end
$version
	Icarus Verilog
$end
$timescale
	1ps
$end
$scope module imem_tb $end
$var wire 32 ! rd [31:0] $end
$var reg 1 " IM_R $end
$var reg 32 # a [31:0] $end
$var integer 32 $ i [31:0] $end
$scope module imem1 $end
$var wire 1 " IM_R $end
$var wire 32 % a [31:0] $end
$var wire 32 & rd [31:0] $end
$upscope $end
$upscope $end
$enddefinitions $end
#0
$dumpvars
b0 &
b0 %
b0 $
b0 #
1"
b0 !
$end
#10000
b110100000000010000000000000001 !
b110100000000010000000000000001 &
b1 $
b100 #
b100 %
#20000
b110100000000101111111111111111 !
b110100000000101111111111111111 &
b10 $
b1000 #
b1000 %
#30000
b100001010000000000 !
b100001010000000000 &
b11 $
b1100 #
b1100 %
#40000
b110100010000101111111111111111 !
b110100010000101111111111111111 &
b100 $
b10000 #
b10000 %
#50000
b110100000000111000000000000000 !
b110100000000111000000000000000 &
b101 $
b10100 #
b10100 %
#60000
b110001110000000000 !
b110001110000000000 &
b110 $
b11000 #
b11000 %
#70000
b110100000001000000000000000000 !
b110100000001000000000000000000 &
b111 $
b11100 #
b11100 %
#80000
b110100000001010000000000000001 !
b110100000001010000000000000001 &
b1000 $
b100000 #
b100000 %
#90000
b110100000001100000000000000010 !
b110100000001100000000000000010 &
b1001 $
b100100 #
b100100 %
#100000
b110100000001110000000000000011 !
b110100000001110000000000000011 &
b1010 $
b101000 #
b101000 %
#110000
b110100000010000000000000000100 !
b110100000010000000000000000100 &
b1011 $
b101100 #
b101100 %
#120000
b110100000010010000000000000101 !
b110100000010010000000000000101 &
b1100 $
b110000 #
b110000 %
#130000
b110100000010100000000000000110 !
b110100000010100000000000000110 &
b1101 $
b110100 #
b110100 %
#140000
b110100000010110000000000000111 !
b110100000010110000000000000111 &
b1110 $
b111000 #
b111000 %
#150000
b110100000011000000000000001000 !
b110100000011000000000000001000 &
b1111 $
b111100 #
b111100 %
#160000
b110100000011010000000000001001 !
b110100000011010000000000001001 &
b10000 $
b1000000 #
b1000000 %
#170000
b110100000011100000000000001010 !
b110100000011100000000000001010 &
b10001 $
b1000100 #
b1000100 %
#180000
b110100000011110000000000001011 !
b110100000011110000000000001011 &
b10010 $
b1001000 #
b1001000 %
#190000
b110100000100000000000000001100 !
b110100000100000000000000001100 &
b10011 $
b1001100 #
b1001100 %
#200000
b110100000100010000000000001101 !
b110100000100010000000000001101 &
b10100 $
b1010000 #
b1010000 %
#210000
b110100000100100000000000001110 !
b110100000100100000000000001110 &
b10101 $
b1010100 #
b1010100 %
#220000
b110100000100111111000000000000 !
b110100000100111111000000000000 &
b10110 $
b1011000 #
b1011000 %
#230000
b100111001110000000000 !
b100111001110000000000 &
b10111 $
b1011100 #
b1011100 %
#240000
b110100000101001111111111111111 !
b110100000101001111111111111111 &
b11000 $
b1100000 #
b1100000 %
#250000
b101001010010000000000 !
b101001010010000000000 &
b11001 $
b1100100 #
b1100100 %
#260000
b110110100101001000000000000000 !
b110110100101001000000000000000 &
b11010 $
b1101000 #
b1101000 %
#270000
b110100000101011000000000000000 !
b110100000101011000000000000000 &
b11011 $
b1101100 #
b1101100 %
#280000
b101011010110000000000 !
b101011010110000000000 &
b11100 $
b1110000 #
b1110000 %
#290000
b110100000101101111111111111111 !
b110100000101101111111111111111 &
b11101 $
b1110100 #
b1110100 %
#300000
b101101011010000000000 !
b101101011010000000000 &
b11110 $
b1111000 #
b1111000 %
#310000
b110110110101101111111111111111 !
b110110110101101111111111111111 &
b11111 $
b1111100 #
b1111100 %
#320000
b110100000101111111111111111111 !
b110100000101111111111111111111 &
b100000 $
b10000000 #
b10000000 %
#330000
b101111011110000000000 !
b101111011110000000000 &
b100001 $
b10000100 #
b10000100 %
#340000
b110110111101111111111111110000 !
b110110111101111111111111110000 &
b100010 $
b10001000 #
b10001000 %
#350000
b110100000110001000111111111111 !
b110100000110001000111111111111 &
b100011 $
b10001100 #
b10001100 %
#360000
b110001100010000000000 !
b110001100010000000000 &
b100100 $
b10010000 #
b10010000 %
#370000
b110100000110011001111111111111 !
b110100000110011001111111111111 &
b100101 $
b10010100 #
b10010100 %
#380000
b110011100110000000000 !
b110011100110000000000 &
b100110 $
b10011000 #
b10011000 %
#390000
b110100000110101110111111111111 !
b110100000110101110111111111111 &
b100111 $
b10011100 #
b10011100 %
#400000
b110101101010000000000 !
b110101101010000000000 &
b101000 $
b10100000 #
b10100000 %
#410000
b110100000110111000111100110000 !
b110100000110111000111100110000 &
b101001 $
b10100100 #
b10100100 %
#420000
b110111101110000000000 !
b110111101110000000000 &
b101010 $
b10101000 #
b10101000 %
#430000
b110100000111001000000000011100 !
b110100000111001000000000011100 &
b101011 $
b10101100 #
b10101100 %
#440000
b111001110010000000000 !
b111001110010000000000 &
b101100 $
b10110000 #
b10110000 %
#450000
b110100000111011000000000011101 !
b110100000111011000000000011101 &
b101101 $
b10110100 #
b10110100 %
#460000
b111011110110000000000 !
b111011110110000000000 &
b101110 $
b10111000 #
b10111000 %
#470000
b110100000111101000000000011110 !
b110100000111101000000000011110 &
b101111 $
b10111100 #
b10111100 %
#480000
b111101111010000000000 !
b111101111010000000000 &
b110000 $
b11000000 #
b11000000 %
#490000
b110100000111111000000000011111 !
b110100000111111000000000011111 &
b110001 $
b11000100 #
b11000100 %
#500000
b111111111110000000000 !
b111111111110000000000 &
b110010 $
b11001000 #
b11001000 %
#510000
b100001 !
b100001 &
b110011 $
b11001100 #
b11001100 %
#520000
b10000000000100001 !
b10000000000100001 &
b110100 $
b11010000 #
b11010000 %
#530000
b100000000000100001 !
b100000000000100001 &
b110101 $
b11010100 #
b11010100 %
#540000
b110000000000100001 !
b110000000000100001 &
b110110 $
b11011000 #
b11011000 %
#550000
b100000000010000000100001 !
b100000000010000000100001 &
b110111 $
b11011100 #
b11011100 %
#560000
b100000010010000000100001 !
b100000010010000000100001 &
b111000 $
b11100000 #
b11100000 %
#570000
b100000100010000000100001 !
b100000100010000000100001 &
b111001 $
b11100100 #
b11100100 %
#580000
b100000110010000000100001 !
b100000110010000000100001 &
b111010 $
b11101000 #
b11101000 %
#590000
b101000000010100000100001 !
b101000000010100000100001 &
b111011 $
b11101100 #
b11101100 %
#600000
b101000010010100000100001 !
b101000010010100000100001 &
b111100 $
b11110000 #
b11110000 %
